{
  "main": {
    "id": "7b793816d23c7d05",
    "type": "split",
    "children": [
      {
        "id": "00318cc3696ad60d",
        "type": "tabs",
        "children": [
          {
            "id": "5f41c1fe9616faa3",
            "type": "leaf",
            "state": {
              "type": "markdown",
              "state": {
                "file": "中图法分类/【5 - 社会科学】/520 - 教育/家庭教育/穿裙子的儿子.md",
                "mode": "source",
                "source": false
              }
            }
          },
          {
            "id": "781af8c9c73f6d0d",
            "type": "leaf",
            "state": {
              "type": "markdown",
              "state": {
                "file": "中图法分类/【1 - 哲学类】/190 - 伦理学/198 - 职业伦理/198-3. 职业分析/战略迷茫.md",
                "mode": "source",
                "source": false
              }
            }
          },
          {
            "id": "f43544997ed138f2",
            "type": "leaf",
            "state": {
              "type": "markdown",
              "state": {
                "file": "【本周更新】/三碗不过岗.md",
                "mode": "source",
                "source": false
              }
            }
          }
        ],
        "currentTab": 2
      }
    ],
    "direction": "vertical"
  },
  "left": {
    "id": "36883a0dd890aadc",
    "type": "split",
    "children": [
      {
        "id": "27a88da1b223d6ee",
        "type": "tabs",
        "dimension": 39.54285714285714,
        "children": [
          {
            "id": "7569597966c86526",
            "type": "leaf",
            "state": {
              "type": "search",
              "state": {
                "query": "文字张力",
                "matchingCase": true,
                "explainSearch": true,
                "collapseAll": false,
                "extraContext": false,
                "sortOrder": "alphabetical"
              }
            }
          },
          {
            "id": "366372991e7a9040",
            "type": "leaf",
            "state": {
              "type": "bookmarks",
              "state": {}
            }
          }
        ]
      },
      {
        "id": "5cddf796add1364e",
        "type": "tabs",
        "dimension": 60.457142857142856,
        "children": [
          {
            "id": "4879eced09a10136",
            "type": "leaf",
            "state": {
              "type": "file-explorer",
              "state": {
                "sortOrder": "byModifiedTime"
              }
            }
          }
        ]
      }
    ],
    "direction": "horizontal",
    "width": 200
  },
  "right": {
    "id": "667d5636990656b4",
    "type": "split",
    "children": [
      {
        "id": "10b03dbeeae1a19d",
        "type": "tabs",
        "children": [
          {
            "id": "844e37cd2e641078",
            "type": "leaf",
            "state": {
              "type": "backlink",
              "state": {
                "file": "【本周更新】/三碗不过岗.md",
                "collapseAll": true,
                "extraContext": false,
                "sortOrder": "alphabetical",
                "showSearch": false,
                "searchQuery": "",
                "backlinkCollapsed": false,
                "unlinkedCollapsed": true
              }
            }
          },
          {
            "id": "727ef7e1831ef234",
            "type": "leaf",
            "state": {
              "type": "tag",
              "state": {
                "sortOrder": "alphabetical",
                "useHierarchy": true
              }
            }
          }
        ],
        "currentTab": 1
      }
    ],
    "direction": "horizontal",
    "width": 246.5,
    "collapsed": true
  },
  "left-ribbon": {
    "hiddenItems": {
      "switcher:Open quick switcher": false,
      "graph:Open graph view": false,
      "canvas:Create new canvas": false,
      "command-palette:Open command palette": false,
      "markdown-importer:Open format converter": false
    }
  },
  "active": "4879eced09a10136",
  "lastOpenFiles": [
    "【本周更新】/战争艺术.md",
    "【本周更新】/稳妥处置.md",
    "【本周更新】/钢钉.md",
    "【本周更新】/福清帮.md",
    "【本周更新】/包装袋.md",
    "【本周更新】/本味.md",
    "【本周更新】/孔-pop.md",
    "【本周更新】/战胜的可能.md",
    "【本周更新】/鼠头.md",
    "【本周更新】/公有制.md",
    "【本周更新】/中国制造业.md",
    "【本周更新】/格局.md",
    "【本周更新】/血泪史学.md",
    "【本周更新】/无私的价格.md",
    "【本周更新】/一壶浊酒喜相逢.md",
    "【本周更新】/中美导弹.md",
    "【本周更新】/土生土长.md",
    "【本周更新】/死亡搁浅.md",
    "【本周更新】/法网柔情.md",
    "【本周更新】/鸡肋刺身.md",
    "【本周更新】/反仇恨.md",
    "【本周更新】/三碗不过岗.md",
    "中图法分类/【8 - 语言文学类】/810 - 文学总论/三流作家.md",
    "中图法分类/【5 - 社会科学】/520 - 教育/家庭教育/穿裙子的儿子.md",
    "中图法分类/【3 - 自然科学】/360 - 生物科学/龟虽寿.md",
    "Anonymity/01 - 家族答集/里世界.md",
    "6.5/新增",
    "6.5/修订",
    "6.5",
    "5.28/新增",
    "5.28/修订",
    "5.28",
    "Untitled.canvas",
    "5.22/新增",
    "5.22",
    "5.22/修订",
    "中图法分类/【9 - 艺术类】/970 - 技艺/匠心",
    "_附件/Screen Shot 2022-06-10 at 19.46.01.png",
    "_附件/Screen Shot 2022-06-10 at 19.46.07.png",
    "_附件/Screenshot 2022-12-02 at 11.01.55.png",
    "待移除/_附件/Screen Shot 2022-06-10 at 19.46.07.png",
    "待移除/_附件/Screenshot 2022-12-02 at 11.01.55.png",
    "待移除/_附件/Screenshot 2022-12-31 at 07.25.12.png",
    "待移除/_附件/Screenshot 2022-12-31 at 07.25.21.png",
    "待移除/_附件/Screenshot 2022-12-31 at 07.25.27.png",
    "待移除/_附件/Screenshot 2022-12-31 at 07.25.34.png",
    "转载授权/2-授权条款更新.png"
  ]
}