{
  "main": {
    "id": "7b793816d23c7d05",
    "type": "split",
    "children": [
      {
        "id": "993c8656c0255eb4",
        "type": "tabs",
        "children": [
          {
            "id": "5d08851cdb62882c",
            "type": "leaf",
            "state": {
              "type": "empty",
              "state": {}
            }
          }
        ]
      }
    ],
    "direction": "vertical"
  },
  "left": {
    "id": "36883a0dd890aadc",
    "type": "split",
    "children": [
      {
        "id": "27a88da1b223d6ee",
        "type": "tabs",
        "dimension": 33.77403846153846,
        "children": [
          {
            "id": "7569597966c86526",
            "type": "leaf",
            "state": {
              "type": "search",
              "state": {
                "query": "",
                "matchingCase": false,
                "explainSearch": true,
                "collapseAll": false,
                "extraContext": false,
                "sortOrder": "byCreatedTimeReverse"
              }
            }
          },
          {
            "id": "366372991e7a9040",
            "type": "leaf",
            "state": {
              "type": "bookmarks",
              "state": {}
            }
          }
        ]
      },
      {
        "id": "5cddf796add1364e",
        "type": "tabs",
        "dimension": 66.22596153846153,
        "children": [
          {
            "id": "4879eced09a10136",
            "type": "leaf",
            "state": {
              "type": "file-explorer",
              "state": {
                "sortOrder": "byModifiedTime"
              }
            }
          }
        ]
      }
    ],
    "direction": "horizontal",
    "width": 241.5
  },
  "right": {
    "id": "667d5636990656b4",
    "type": "split",
    "children": [
      {
        "id": "10b03dbeeae1a19d",
        "type": "tabs",
        "children": [
          {
            "id": "844e37cd2e641078",
            "type": "leaf",
            "state": {
              "type": "backlink",
              "state": {
                "collapseAll": true,
                "extraContext": false,
                "sortOrder": "alphabetical",
                "showSearch": false,
                "searchQuery": "",
                "backlinkCollapsed": false,
                "unlinkedCollapsed": true
              }
            }
          },
          {
            "id": "727ef7e1831ef234",
            "type": "leaf",
            "state": {
              "type": "tag",
              "state": {
                "sortOrder": "alphabetical",
                "useHierarchy": true
              }
            }
          },
          {
            "id": "bf225de6acac63ea",
            "type": "leaf",
            "state": {
              "type": "all-properties",
              "state": {
                "sortOrder": "frequency",
                "showSearch": false,
                "searchQuery": ""
              }
            }
          }
        ],
        "currentTab": 1
      }
    ],
    "direction": "horizontal",
    "width": 262.5,
    "collapsed": true
  },
  "left-ribbon": {
    "hiddenItems": {
      "switcher:Open quick switcher": false,
      "graph:Open graph view": false,
      "canvas:Create new canvas": false,
      "command-palette:Open command palette": false,
      "markdown-importer:Open format converter": false
    }
  },
  "active": "5d08851cdb62882c",
  "lastOpenFiles": [
    "【本周更新】/向后看.md",
    "【文章目录】/【1 - 哲学类】/160 - 形而上学/162 - 方法论/论健康/华容道.md",
    "【本周更新】/共情能力.md",
    "【本周更新】/出头鸟.md",
    "【本周更新】/现实问题.md",
    "【本周更新】/未成年驱动器.md",
    "【本周更新】/性感与女王.md",
    "【本周更新】/好大棺材.md",
    "【本周更新】/以和为贵.md",
    "【本周更新】/婴儿战车.md",
    "【本周更新】/厌物.md",
    "【本周更新】/完整规定.md",
    "【本周更新】/聪明正直.md",
    "【本周更新】/鬼故事.md",
    "【本周更新】/早期干预.md",
    "【本周更新】/逆行超车.md",
    "【本周更新】/监守者难辞其咎.md",
    "【本周更新】/外资医院.md",
    "待归档/铁布衫.md",
    "md/2024-09-12怎么样能改掉好了伤疤忘了疼的毛病？.md",
    "md/2024-09-09为什么整个中国都知道中国足球的问题，为什么还是没有办法解决？.md",
    "待归档/体育问题.md",
    "md/2024-09-08当孩子提出无理要求时，家长应该怎么做？.md",
    "md/2024-09-08人如何克服自己的懒散习性？.md",
    "待归档/LEGEN~DARY.md",
    "待归档/礼貌的意义.md",
    "md",
    "md/Nel",
    "爱的原理",
    "md/N",
    "md/Nell",
    "md/N",
    "【文章目录】/【2 - 信仰类】/神学评论区",
    "爱发电/南斗集",
    "爱发电",
    "爱发电/会员专享",
    "转载授权/1-鼓励利用我的内容盈利.jpeg",
    "转载授权/2-授权条款更新.png",
    "_附件/Screenshot 2022-12-02 at 11.01.55.png",
    "_附件/Screen Shot 2022-06-10 at 19.46.07.png",
    "_附件/Screen Shot 2022-06-10 at 19.46.01.png",
    "Untitled.canvas",
    "待移除/_附件/Screen Shot 2022-06-10 at 19.46.07.png",
    "待移除/_附件/Screenshot 2022-12-02 at 11.01.55.png",
    "待移除/_附件/Screenshot 2022-12-31 at 07.25.12.png",
    "待移除/_附件/Screenshot 2022-12-31 at 07.25.21.png",
    "待移除/_附件/Screenshot 2022-12-31 at 07.25.27.png"
  ]
}